open_meteo/__init__.py
open_meteo/exceptions.py
open_meteo/models.py
open_meteo/open_meteo.py
open_meteo/py.typed
open_meteo-0.4.0.dist-info/METADATA
open_meteo-0.4.0.dist-info/WHEEL
open_meteo-0.4.0.dist-info/licenses/LICENSE.md
open_meteo-0.4.0.dist-info/RECORD
