Metadata-Version: 2.4
Name: open-meteo
Version: 0.4.0
Summary: Asynchronous client for the Open-Meteo API.
License: MIT
License-File: LICENSE.md
Keywords: weather,weather-api,meteo,openmeteo,open-meteo,api,async,client
Author: Franck Nijhof
Author-email: opensource@frenck.dev
Maintainer: Franck Nijhof
Maintainer-email: opensource@frenck.dev
Requires-Python: >=3.11,<4.0
Classifier: Development Status :: 1 - Planning
Classifier: Intended Audience :: Developers
Classifier: License :: OSI Approved :: MIT License
Classifier: Natural Language :: English
Classifier: Programming Language :: Python :: 3
Classifier: Programming Language :: Python :: 3.11
Classifier: Programming Language :: Python :: 3.12
Classifier: Programming Language :: Python :: 3.13
Classifier: Programming Language :: Python :: 3.14
Classifier: Topic :: Software Development :: Libraries :: Python Modules
Requires-Dist: aiohttp (>=3.8.1)
Requires-Dist: mashumaro (>=3.10)
Requires-Dist: orjson (>=3.9.8)
Project-URL: Bug Tracker, https://github.com/frenck/python-open-meteo/issues
Project-URL: Changelog, https://github.com/frenck/python-open-meteo/releases
Project-URL: Documentation, https://github.com/frenck/python-open-meteo
Project-URL: Homepage, https://github.com/frenck/python-open-meteo
Project-URL: Repository, https://github.com/frenck/python-open-meteo
